PyRook/AutoScroll.py
PyRook/ChatTab.py
PyRook/ChatWindow.py
PyRook/Debug.py
PyRook/Externals.py
PyRook/Find.py
PyRook/FormRequest.py
PyRook/LinkTextBrowser.py
PyRook/Logger.py
PyRook/MessageTab.py
PyRook/PyRook.py
PyRook/Server.py
PyRook/SettingsConvenience.py
PyRook/SettingsDialog.py
PyRook/SpellingLineEdit.py
PyRook/ThemeEngine.py
PyRook/WebTab.py
PyRook/__init__.py
PyRook/__main__.py
PyRook/Importer/QtCore.py
PyRook/Importer/QtGui.py
PyRook/Importer/QtNetwork.py
PyRook/Importer/QtWebKit.py
PyRook/Importer/__init__.py
PyRook/data/PyRook.desktop
PyRook/data/en_US.aff
PyRook/data/en_US.dic
PyRook/data/pyrook_logo.ico
PyRook/data/pyrook_logo.svg
PyRook-0.5.4.dist-info/METADATA
PyRook-0.5.4.dist-info/WHEEL
PyRook-0.5.4.dist-info/entry_points.txt
PyRook-0.5.4.dist-info/top_level.txt
PyRook-0.5.4.dist-info/RECORD
