Metadata-Version: 2.1
Name: PyRook
Version: 0.5.4
Summary: A standalone client for RookChat
Home-page: https://sentynel.com/project/PyRook
Author: Sam Lade
Author-email: pyrook@sentynel.com
License: Public Domain
Keywords: rookchat
Platform: UNKNOWN
Classifier: Development Status :: 4 - Beta
Classifier: Environment :: X11 Applications :: Qt
Classifier: License :: Public Domain
Classifier: Operating System :: OS Independent
Classifier: Programming Language :: Python :: 3 :: Only
Classifier: Programming Language :: Python :: 3.3
Classifier: Programming Language :: Python :: 3.4
Classifier: Programming Language :: Python :: 3.5
Classifier: Topic :: Communications :: Chat
Requires-Dist: lxml
